discbase/Client.py
discbase/__init__.py
discbase/_version.py
discbase/enumeration/BaseEnum.py
discbase/enumeration/URLType.py
discbase/enumeration/__init__.py
discbase/model/KeyValue.py
discbase/model/StoredRecord.py
discbase/model/__init__.py
discbase/model/abstract/DictDeserializable.py
discbase/model/abstract/DictSerializable.py
discbase/model/abstract/Dictizable.py
discbase/model/abstract/__init__.py
discbase/util/CustomFormatter.py
discbase/util/CustomLogger.py
discbase/util/EnvironmentReader.py
discbase/util/__init__.py
discbase/util/error.py
discbase/util/general.py
discbase/util/image.py
test_e2e/__init__.py
test_e2e/test_client_state.py
test_e2e/test_dump.py
test_e2e/test_retrieve.py
test_e2e/util.py
test_unit/__init__.py
test_unit/test_util/__init__.py
test_unit/test_util/test_error.py
test_unit/test_util/test_general.py
discbase-0.5.0.dist-info/LICENSE
discbase-0.5.0.dist-info/METADATA
discbase-0.5.0.dist-info/WHEEL
discbase-0.5.0.dist-info/top_level.txt
discbase-0.5.0.dist-info/RECORD
