Metadata-Version: 2.1
Name: discbase
Version: 0.5.0
Summary: Discord as a Service
Home-page: https://github.com/joeyagreco/discbase
Author: Joey Greco
Author-email: joeyagreco@gmail.com
License: MIT
Keywords: discord database db
Requires-Python: >=3.10
License-File: LICENSE
Requires-Dist: python-dotenv ~=1.0.0
Requires-Dist: discord ~=2.3.1
